wordcounter/__init__.py
wordcounter/wordcounter.py
wordcounterpy-0.1.dist-info/METADATA
wordcounterpy-0.1.dist-info/WHEEL
wordcounterpy-0.1.dist-info/top_level.txt
wordcounterpy-0.1.dist-info/RECORD
